phecoder/__init__.py
phecoder/_defaults.py
phecoder/_embed.py
phecoder/_ensemble.py
phecoder/_evaluate.py
phecoder/_similarity.py
phecoder/phecoder.py
phecoder/utils.py
phecoder-0.1.1.dist-info/METADATA
phecoder-0.1.1.dist-info/WHEEL
phecoder-0.1.1.dist-info/licenses/LICENSE
phecoder-0.1.1.dist-info/RECORD
