Metadata-Version: 2.4
Name: phecoder
Version: 0.1.1
Summary: Semantic retrieval for auditing and expanding ICD-based phenotypes in EHR biobanks.
License: Apache-2.0
License-File: LICENSE
Keywords: Phenotyping,Phecodes,ICD-9,ICD-10,Transformer Networks,Semantic search,PyTorch,NLP,Deep learning
Author: Jamie Bennett, Sonali Gupta, David Burstein
Requires-Python: >=3.10,<3.14
Classifier: Intended Audience :: Science/Research
Classifier: License :: OSI Approved :: Apache Software License
Classifier: Programming Language :: Python :: 3
Classifier: Programming Language :: Python :: 3.10
Classifier: Programming Language :: Python :: 3.11
Classifier: Programming Language :: Python :: 3.12
Classifier: Programming Language :: Python :: 3.13
Classifier: Topic :: Scientific/Engineering :: Artificial Intelligence
Requires-Dist: ipykernel (>=6.30.1,<7.0.0)
Requires-Dist: openpyxl (>=3.1.5,<4.0.0)
Requires-Dist: pandas (>=2.3.2,<3.0.0)
Requires-Dist: pyarrow (>=21.0.0,<22.0.0)
Requires-Dist: sentence-transformers (>=5.1.0,<6.0.0)
Project-URL: Homepage, https://github.com/03bennej/phecoder.git
